{
    "name": "Open Domain DAO",
    "website": "https://opendomaindao.com",
    "description": "Open Domain DAO is a decentralized autonomous venture capital fund: By pooling capital and investors, deploying investment plans, the Open Domain DAO Funding Funds”, DAO means investment management portfolio.",
    "explorer": "https://bscscan.com/token/0x5a5c71f8A41bfbA05aE9f7833D2cd89508a1f998",
    "type": "BEP20",
    "symbol": "ODO",
    "decimals": 18,
    "status": "active",
    "id": "0x5a5c71f8A41bfbA05aE9f7833D2cd89508a1f998"
}