{
    "name": "AKT",
    "website": "",
    "description": "AKT is a visionary project aimed at establishing a decentralized AI platform where various AI algorithms and tools can collaborate and communicate with each other. By establishing a decentralized AI platform and intelligent world, we have the potential to achieve more efficient and secure artificial intelligence applications. This will have profound impacts on various fields.",
    "explorer": "https://polygonscan.com/address/0x76f8a10265865376e4f90f6d78262d2d55f4c853",
    "type": "Polygon",
    "symbol": "AKT",
    "decimals": 18,
    "status": "active",
    "id": "0x76f8a10265865376e4f90f6d78262d2d55f4c853"
   }